tomskit/__init__.py
tomskit/config.py
tomskit/py.typed
tomskit/celery/README.md
tomskit/celery/__init__.py
tomskit/celery/celery.py
tomskit/celery/config.py
tomskit/celery/context.py
tomskit/celery/orjson_serializer.py
tomskit/cli/__init__.py
tomskit/cli/__main__.py
tomskit/cli/scaffold.py
tomskit/cli/templates_config.py
tomskit/cli/templates/__init__.py
tomskit/cli/templates/base/__init__.py
tomskit/cli/templates/base/env_example.py
tomskit/cli/templates/base/gitignore.py
tomskit/cli/templates/base/pyproject_toml.py
tomskit/cli/templates/base/readme.py
tomskit/cli/templates/celery/__init__.py
tomskit/cli/templates/celery/celery_app.py
tomskit/cli/templates/celery/example_task.py
tomskit/cli/templates/celery/tasks_init.py
tomskit/cli/templates/configs/__init__.py
tomskit/cli/templates/configs/init.py
tomskit/cli/templates/configs/pyproject.py
tomskit/cli/templates/configs/settings.py
tomskit/cli/templates/extensions/__init__.py
tomskit/cli/templates/extensions/ext_celery.py
tomskit/cli/templates/extensions/ext_database.py
tomskit/cli/templates/extensions/ext_logger.py
tomskit/cli/templates/extensions/ext_modules.py
tomskit/cli/templates/extensions/ext_redis.py
tomskit/cli/templates/extensions/ext_warnings.py
tomskit/cli/templates/fastapi/__init__.py
tomskit/cli/templates/fastapi/app_factory.py
tomskit/cli/templates/fastapi/app_init.py
tomskit/cli/templates/fastapi/controllers_init.py
tomskit/cli/templates/fastapi/main.py
tomskit/cli/templates/fastapi/middleware_init.py
tomskit/cli/templates/fastapi/middleware_request_id.py
tomskit/cli/templates/fastapi/middleware_resource_cleanup.py
tomskit/cli/templates/fastapi/models_init.py
tomskit/cli/templates/fastapi/test_users.py
tomskit/cli/templates/fastapi/user_model.py
tomskit/cli/templates/fastapi/users_init.py
tomskit/cli/templates/fastapi/users_module.py
tomskit/cli/templates/fastapi/users_resources.py
tomskit/cli/templates/fastapi/users_schemas.py
tomskit/cli/templates/migrations/__init__.py
toms_fast-0.3.13.dist-info/METADATA
toms_fast-0.3.13.dist-info/WHEEL
toms_fast-0.3.13.dist-info/entry_points.txt
toms_fast-0.3.13.dist-info/RECORD
