Metadata-Version: 2.4
Name: toms-fast
Version: 0.3.13
Summary: 基于 FastAPI 的异步基础工具库，提供 Redis、SQLAlchemy、Celery、日志管理等企业级基础设施的统一封装，简化异步 API 与服务端应用开发（import 包名：tomskit）
Author-email: AllinOneAI Team <ai@aioai.cc>
Requires-Python: >=3.11
Requires-Dist: alembic>=1.13.0
Requires-Dist: celery>=5.5.2
Requires-Dist: fastapi>=0.115.12
Requires-Dist: orjson>=3.9.0
Requires-Dist: pydantic-settings>=2.9.1
Requires-Dist: redis>=6.0.0
Requires-Dist: sqlalchemy>=2.0.40
